LICENSE
MANIFEST.in
README.md
requirements.txt
setup.py
django_static_html5shiv/__init__.py
django_static_html5shiv/admin.py
django_static_html5shiv/apps.py
django_static_html5shiv/models.py
django_static_html5shiv/tests.py
django_static_html5shiv/views.py
django_static_html5shiv.egg-info/PKG-INFO
django_static_html5shiv.egg-info/SOURCES.txt
django_static_html5shiv.egg-info/dependency_links.txt
django_static_html5shiv.egg-info/not-zip-safe
django_static_html5shiv.egg-info/top_level.txt
django_static_html5shiv/migrations/__init__.py
django_static_html5shiv/static/.DS_Store
django_static_html5shiv/static/html5shiv/html5shiv-printshiv.js
django_static_html5shiv/static/html5shiv/html5shiv-printshiv.min.js
django_static_html5shiv/static/html5shiv/html5shiv.js
django_static_html5shiv/static/html5shiv/html5shiv.min.js