Metadata-Version: 2.1
Name: django-static-html5shiv
Version: 3.7.3.3
Summary: Django application contain html5shiv static files.
Home-page: https://github.com/zencore-cn/zencore-issues
Author: zencore
Author-email: dobetter@zencore.cn
License: MIT
Keywords: django-static-html5shiv
Platform: UNKNOWN
Classifier: Development Status :: 5 - Production/Stable
Classifier: Intended Audience :: Developers
Classifier: Topic :: Software Development :: Libraries :: Python Modules
Classifier: License :: OSI Approved :: MIT License
Classifier: Programming Language :: Python :: 3
Classifier: Programming Language :: Python :: 3 :: Only
